hyperjax/__init__.py
hyperjax/generator.py
hyperjax/operation.py
hyper_jax-0.0.1.dist-info/LICENSE
hyper_jax-0.0.1.dist-info/METADATA
hyper_jax-0.0.1.dist-info/WHEEL
hyper_jax-0.0.1.dist-info/top_level.txt
hyper_jax-0.0.1.dist-info/RECORD
