Metadata-Version: 2.1
Name: hyper-jax
Version: 0.0.1
Summary: Hyperdimensional computing with Jax
Author-email: marklar <ddillon@gmail.com>
License: MIT License
Keywords: hyperdimensional computing,jax,vector symbolic architecture
Classifier: License :: OSI Approved :: MIT License
Classifier: Programming Language :: Python
Classifier: Programming Language :: Python :: 3
Requires-Python: >=3.10
License-File: LICENSE
Requires-Dist: jax >=0.4.19
